cbpro/.gitignore
cbpro/__init__.py
cbpro/authenticated_client.py
cbpro/cbpro_auth.py
cbpro/public_client.py
coinbasepro_revived-1.1.12.dist-info/LICENSE
coinbasepro_revived-1.1.12.dist-info/WHEEL
coinbasepro_revived-1.1.12.dist-info/METADATA
coinbasepro_revived-1.1.12.dist-info/RECORD
